CHANGELOG.md
fameprotobuf/__init__.py
fameprotobuf/agent_message_pb2.py
fameprotobuf/agent_message_pb2.pyi
fameprotobuf/bundle_pb2.py
fameprotobuf/bundle_pb2.pyi
fameprotobuf/contract_pb2.py
fameprotobuf/contract_pb2.pyi
fameprotobuf/data_storage_pb2.py
fameprotobuf/data_storage_pb2.pyi
fameprotobuf/execution_data_pb2.py
fameprotobuf/execution_data_pb2.pyi
fameprotobuf/field_pb2.py
fameprotobuf/field_pb2.pyi
fameprotobuf/input_file_pb2.py
fameprotobuf/input_file_pb2.pyi
fameprotobuf/model_pb2.py
fameprotobuf/model_pb2.pyi
fameprotobuf/services_pb2.py
fameprotobuf/services_pb2.pyi
fameprotobuf-2.1.0.dist-info/LICENSE
fameprotobuf-2.1.0.dist-info/LICENSES/Apache-2.0.txt
fameprotobuf-2.1.0.dist-info/LICENSES/CC0-1.0.txt
fameprotobuf-2.1.0.dist-info/METADATA
fameprotobuf-2.1.0.dist-info/WHEEL
fameprotobuf-2.1.0.dist-info/RECORD
