Metadata-Version: 2.1
Name: fameprotobuf
Version: 2.1.0
Summary: Protobuf definitions converted to python classes for use in `fameio`
Home-page: https://gitlab.com/fame-framework/wiki/-/wikis/home
License: Apache-2.0
Keywords: protobuffer,FAME,framework,fameio,agent-based modelling
Author: Christoph Schimeczek
Author-email: fame@dlr.de
Maintainer: Christoph Schimeczek
Maintainer-email: fame@dlr.de
Requires-Python: >=3.8,<4.0
Classifier: Development Status :: 5 - Production/Stable
Classifier: License :: OSI Approved :: Apache Software License
Classifier: Operating System :: OS Independent
Classifier: Programming Language :: Python :: 3
Classifier: Programming Language :: Python :: 3.8
Classifier: Programming Language :: Python :: 3.9
Classifier: Programming Language :: Python :: 3.10
Classifier: Programming Language :: Python :: 3.11
Classifier: Topic :: Scientific/Engineering
Requires-Dist: protobuf (>=4.21.1,<5.0.0)
Project-URL: Repository, https://gitlab.com/fame-framework/fame-protobuf
